dakia/__init__.py
dakia/dakia.py
dakia-0.0.3.dist-info/LICENSE
dakia-0.0.3.dist-info/METADATA
dakia-0.0.3.dist-info/WHEEL
dakia-0.0.3.dist-info/top_level.txt
dakia-0.0.3.dist-info/RECORD
