Metadata-Version: 2.1
Name: dakia
Version: 0.0.3
Summary: Send yourself real time alerts and update messages about your projects on any platform
Home-page: https://github.com/allwynfernandes/dakia
Author: Allwyn Fernandes
Author-email: thisallwyn@gmail.com
License: UNKNOWN
Keywords: logging,updates,alerts,debug,notification
Platform: UNKNOWN
Classifier: Topic :: Utilities
Classifier: Topic :: System :: Networking :: Monitoring
Classifier: Topic :: System :: Monitoring
Classifier: Topic :: System :: Logging
Classifier: Topic :: Software Development :: Debuggers
Classifier: Topic :: Communications :: Chat
Classifier: Programming Language :: Python :: 3.11
Classifier: Programming Language :: Python :: 3.10
Classifier: Programming Language :: Python :: 3.9
Classifier: Programming Language :: Python :: 3.8
Classifier: Programming Language :: Python :: 3.7
Classifier: Programming Language :: Python :: 3.6
Classifier: Programming Language :: Python :: 3
Classifier: Operating System :: OS Independent
Classifier: Intended Audience :: Developers
Classifier: Intended Audience :: Customer Service
Classifier: Intended Audience :: Education
Classifier: Development Status :: 5 - Production/Stable
Requires-Python: >=3.6
License-File: LICENSE
Requires-Dist: requests
